macronet/__init__.py
macronet/_monet.py
macronet/base.py
macronet/defdef.py
macronet/example.py
macronet/flowfunc.py
macronet/torch_ddf.py
MacroNet-0.1.1.dist-info/METADATA
MacroNet-0.1.1.dist-info/WHEEL
MacroNet-0.1.1.dist-info/top_level.txt
MacroNet-0.1.1.dist-info/RECORD
